arp_conformance/__init__.py
arp_conformance/api.py
arp_conformance/cli.py
arp_conformance/http.py
arp_conformance/py.typed
arp_conformance/report.py
arp_conformance/runner.py
arp_conformance/schemas.py
arp_conformance/spec_loader.py
arp_conformance/_spec/v1/CHANGELOG.md
arp_conformance/_spec/v1/README.md
arp_conformance/_spec/v1/conformance/README.md
arp_conformance/_spec/v1/conformance/json_vectors/README.md
arp_conformance/_spec/v1/conformance/json_vectors/atomic_executor/node_runs/atomic_execute_request.json
arp_conformance/_spec/v1/conformance/json_vectors/atomic_executor/node_runs/atomic_execute_result.json
arp_conformance/_spec/v1/conformance/json_vectors/common/endpoint_locator.json
arp_conformance/_spec/v1/conformance/json_vectors/common/error.json
arp_conformance/_spec/v1/conformance/json_vectors/common/error_cause.json
arp_conformance/_spec/v1/conformance/json_vectors/common/error_detail.json
arp_conformance/_spec/v1/conformance/json_vectors/common/extensions.json
arp_conformance/_spec/v1/conformance/json_vectors/common/health.json
arp_conformance/_spec/v1/conformance/json_vectors/common/metadata.json
arp_conformance/_spec/v1/conformance/json_vectors/common/pagination.json
arp_conformance/_spec/v1/conformance/json_vectors/common/resource_ref.json
arp_conformance/_spec/v1/conformance/json_vectors/common/status.json
arp_conformance/_spec/v1/conformance/json_vectors/common/version_info.json
arp_conformance/_spec/v1/conformance/json_vectors/composite_executor/node_runs/composite_begin_request.json
arp_conformance/_spec/v1/conformance/json_vectors/composite_executor/node_runs/composite_begin_response.json
arp_conformance/_spec/v1/conformance/json_vectors/core/approval_ref.json
arp_conformance/_spec/v1/conformance/json_vectors/core/binding_decision.json
arp_conformance/_spec/v1/conformance/json_vectors/core/candidate.json
arp_conformance/_spec/v1/conformance/json_vectors/core/candidate_set.json
arp_conformance-0.3.7.dist-info/licenses/LICENSE
arp_conformance-0.3.7.dist-info/METADATA
arp_conformance-0.3.7.dist-info/WHEEL
arp_conformance-0.3.7.dist-info/entry_points.txt
arp_conformance-0.3.7.dist-info/top_level.txt
arp_conformance-0.3.7.dist-info/RECORD
